yalafi/__init__.py
yalafi/__main__.py
yalafi/defs.py
yalafi/handlers.py
yalafi/mathparser.py
yalafi/parameters.py
yalafi/parser.py
yalafi/scanner.py
yalafi/tex2txt.py
yalafi/utils.py
yalafi/documentclasses/__init__.py
yalafi/documentclasses/article.py
yalafi/documentclasses/book.py
yalafi/documentclasses/report.py
yalafi/documentclasses/scrartcl.py
yalafi/documentclasses/scrbook.py
yalafi/documentclasses/scrreprt.py
yalafi/packages/__init__.py
yalafi/packages/amsmath.py
yalafi/packages/amsthm.py
yalafi/packages/babel.py
yalafi/packages/biblatex.py
yalafi/packages/circuitikz.py
yalafi/packages/cleveref.py
yalafi/packages/geometry.py
yalafi/packages/glossaries.py
yalafi/packages/glossaries_extra.py
yalafi/packages/graphicx.py
yalafi/packages/hyperref.py
yalafi/packages/inputenc.py
yalafi/packages/koma_script.py
yalafi/packages/listings.py
yalafi/packages/mathtools.py
yalafi/packages/pgfplots.py
yalafi/packages/subfiles.py
yalafi/packages/tikz.py
yalafi/packages/unicode_math.py
yalafi/packages/xcolor.py
yalafi/packages/xspace.py
yalafi/shell/__init__.py
yalafi/shell/__main__.py
yalafi/shell/addpacks.py
yalafi/shell/checks.py
yalafi/shell/genhtml.py
yalafi/shell/genjson.py
yalafi/shell/gentext.py
yalafi/shell/genxml.py
yalafi/shell/proofreader.py
yalafi/shell/server.py
yalafi/shell/shell.py
yalafi/shell/utils.py
yalafi-1.5.0.dist-info/LICENSE
yalafi-1.5.0.dist-info/METADATA
yalafi-1.5.0.dist-info/WHEEL
yalafi-1.5.0.dist-info/top_level.txt
yalafi-1.5.0.dist-info/RECORD
