Metadata-Version: 2.1
Name: yalafi
Version: 1.5.0
Summary: Yet another LaTeX filter
Author: Matthias Baumann, torik42
Project-URL: Homepage, https://github.com/torik42/YaLafi
Project-URL: Changelog, https://github.com/torik42/YaLafi/blob/master/HISTORY.md
Project-URL: Documentation, https://github.com/torik42/YaLafi#contents
Project-URL: Issue Tracker, https://github.com/torik42/YaLafi/issues
Classifier: Programming Language :: Python :: 3
Classifier: License :: OSI Approved :: GNU General Public License v3 (GPLv3)
Classifier: Operating System :: OS Independent
Classifier: Topic :: Text Processing :: Markup :: LaTeX
Classifier: Topic :: Text Processing :: Filters
License-File: LICENSE
